pubmed_id/__init__.py
pubmed_id/__main__.py
pubmed_id/api.py
pubmed_id/cli.py
pubmed_id-1.1.dist-info/METADATA
pubmed_id-1.1.dist-info/WHEEL
pubmed_id-1.1.dist-info/entry_points.txt
pubmed_id-1.1.dist-info/top_level.txt
pubmed_id-1.1.dist-info/RECORD
