Metadata-Version: 2.1
Name: pubmed-id
Version: 1.1
Summary: Simple interface to query or scrape IDs from PubMed.
Author-email: Nelson Aloysio Reis de Almeida Passos <nelson.reis@phd.unipi.it>
Project-URL: Homepage, https://pypi.org/p/pubmed-id/
Project-URL: Repository, https://github.com/nelsonaloysio/pubmed-id
Project-URL: Issues, https://github.com/nelsonaloysio/pubmed-id/issues
Project-URL: Changelog, https://github.com/nelsonaloysio/pubmed-id/blob/main/CHANGELOG.md
Keywords: PubMed
Classifier: Development Status :: 5 - Production/Stable
Classifier: Intended Audience :: Developers
Classifier: Intended Audience :: Information Technology
Classifier: Intended Audience :: Science/Research
Classifier: License :: OSI Approved :: MIT License
Classifier: Programming Language :: Python :: 3
Classifier: Topic :: Scientific/Engineering :: Information Analysis
Classifier: Topic :: Software Development :: Libraries :: Python Modules
Requires-Python: >=3.7
Requires-Dist: beautifulsoup4 >=4.9.3
Requires-Dist: requests >=2.31.0
Requires-Dist: tqdm >=4.65.0
